[{"n_PhaseID":109556,"n_PhaseLevel":162,"c_Phase":"Kwalificatieronde 1","n_Phase1ID":109554,"n_Phase1Nr":1,"c_Phase1":"Kwalificatie","n_Phase2ID":109556,"n_Phase2Nr":1,"c_Phase2":"Kwalificatieronde 1","n_Phase3ID":null,"n_Phase3Nr":null,"c_Phase3":null,"b_Table":false,"b_Current":false,"b_Currents":false,"n_DateStart":20140701,"n_DateEnd":20140711},{"n_PhaseID":109557,"n_PhaseLevel":122,"c_Phase":"Kwalificatieronde 2","n_Phase1ID":109554,"n_Phase1Nr":1,"c_Phase1":"Kwalificatie","n_Phase2ID":109557,"n_Phase2Nr":2,"c_Phase2":"Kwalificatieronde 2","n_Phase3ID":null,"n_Phase3Nr":null,"c_Phase3":null,"b_Table":false,"b_Current":false,"b_Currents":false,"n_DateStart":20140717,"n_DateEnd":20140724},{"n_PhaseID":109558,"n_PhaseLevel":87,"c_Phase":"Kwalificatieronde 3","n_Phase1ID":109554,"n_Phase1Nr":1,"c_Phase1":"Kwalificatie","n_Phase2ID":109558,"n_Phase2Nr":3,"c_Phase2":"Kwalificatieronde 3","n_Phase3ID":null,"n_Phase3Nr":null,"c_Phase3":null,"b_Table":false,"b_Current":false,"b_Currents":false,"n_DateStart":20140731,"n_DateEnd":20140807},{"n_PhaseID":109559,"n_PhaseLevel":49,"c_Phase":"Play-off ronde","n_Phase1ID":109554,"n_Phase1Nr":1,"c_Phase1":"Kwalificatie","n_Phase2ID":109559,"n_Phase2Nr":4,"c_Phase2":"Play-off ronde","n_Phase3ID":null,"n_Phase3Nr":null,"c_Phase3":null,"b_Table":false,"b_Current":false,"b_Currents":false,"n_DateStart":20140820,"n_DateEnd":20140828},{"n_PhaseID":109566,"n_PhaseLevel":33,"c_Phase":"Groep A","n_Phase1ID":109555,"n_Phase1Nr":2,"c_Phase1":"Hoofdtoernooi","n_Phase2ID":109560,"n_Phase2Nr":5,"c_Phase2":"Groepsfase","n_Phase3ID":109566,"n_Phase3Nr":1,"c_Phase3":"Groep A","b_Table":true,"b_Current":false,"b_Currents":false,"n_DateStart":20140918,"n_DateEnd":20141211},{"n_PhaseID":109567,"n_PhaseLevel":33,"c_Phase":"Groep B","n_Phase1ID":109555,"n_Phase1Nr":2,"c_Phase1":"Hoofdtoernooi","n_Phase2ID":109560,"n_Phase2Nr":5,"c_Phase2":"Groepsfase","n_Phase3ID":109567,"n_Phase3Nr":2,"c_Phase3":"Groep B","b_Table":true,"b_Current":false,"b_Currents":false,"n_DateStart":20140918,"n_DateEnd":20141211},{"n_PhaseID":109568,"n_PhaseLevel":33,"c_Phase":"Groep C","n_Phase1ID":109555,"n_Phase1Nr":2,"c_Phase1":"Hoofdtoernooi","n_Phase2ID":109560,"n_Phase2Nr":5,"c_Phase2":"Groepsfase","n_Phase3ID":109568,"n_Phase3Nr":3,"c_Phase3":"Groep C","b_Table":true,"b_Current":false,"b_Currents":false,"n_DateStart":20140918,"n_DateEnd":20141211},{"n_PhaseID":109569,"n_PhaseLevel":33,"c_Phase":"Groep D","n_Phase1ID":109555,"n_Phase1Nr":2,"c_Phase1":"Hoofdtoernooi","n_Phase2ID":109560,"n_Phase2Nr":5,"c_Phase2":"Groepsfase","n_Phase3ID":109569,"n_Phase3Nr":4,"c_Phase3":"Groep D","b_Table":true,"b_Current":false,"b_Currents":false,"n_DateStart":20140918,"n_DateEnd":20141211},{"n_PhaseID":109570,"n_PhaseLevel":33,"c_Phase":"Groep E","n_Phase1ID":109555,"n_Phase1Nr":2,"c_Phase1":"Hoofdtoernooi","n_Phase2ID":109560,"n_Phase2Nr":5,"c_Phase2":"Groepsfase","n_Phase3ID":109570,"n_Phase3Nr":5,"c_Phase3":"Groep E","b_Table":true,"b_Current":false,"b_Currents":false,"n_DateStart":20140918,"n_DateEnd":20141211},{"n_PhaseID":109571,"n_PhaseLevel":33,"c_Phase":"Groep F","n_Phase1ID":109555,"n_Phase1Nr":2,"c_Phase1":"Hoofdtoernooi","n_Phase2ID":109560,"n_Phase2Nr":5,"c_Phase2":"Groepsfase","n_Phase3ID":109571,"n_Phase3Nr":6,"c_Phase3":"Groep F","b_Table":true,"b_Current":false,"b_Currents":false,"n_DateStart":20140918,"n_DateEnd":20141211},{"n_PhaseID":109572,"n_PhaseLevel":33,"c_Phase":"Groep G","n_Phase1ID":109555,"n_Phase1Nr":2,"c_Phase1":"Hoofdtoernooi","n_Phase2ID":109560,"n_Phase2Nr":5,"c_Phase2":"Groepsfase","n_Phase3ID":109572,"n_Phase3Nr":7,"c_Phase3":"Groep G","b_Table":true,"b_Current":false,"b_Currents":false,"n_DateStart":20140918,"n_DateEnd":20141211},{"n_PhaseID":109573,"n_PhaseLevel":33,"c_Phase":"Groep H","n_Phase1ID":109555,"n_Phase1Nr":2,"c_Phase1":"Hoofdtoernooi","n_Phase2ID":109560,"n_Phase2Nr":5,"c_Phase2":"Groepsfase","n_Phase3ID":109573,"n_Phase3Nr":8,"c_Phase3":"Groep H","b_Table":true,"b_Current":false,"b_Currents":false,"n_DateStart":20140918,"n_DateEnd":20141211},{"n_PhaseID":109574,"n_PhaseLevel":33,"c_Phase":"Groep I","n_Phase1ID":109555,"n_Phase1Nr":2,"c_Phase1":"Hoofdtoernooi","n_Phase2ID":109560,"n_Phase2Nr":5,"c_Phase2":"Groepsfase","n_Phase3ID":109574,"n_Phase3Nr":9,"c_Phase3":"Groep I","b_Table":true,"b_Current":false,"b_Currents":false,"n_DateStart":20140918,"n_DateEnd":20141211},{"n_PhaseID":109575,"n_PhaseLevel":33,"c_Phase":"Groep J","n_Phase1ID":109555,"n_Phase1Nr":2,"c_Phase1":"Hoofdtoernooi","n_Phase2ID":109560,"n_Phase2Nr":5,"c_Phase2":"Groepsfase","n_Phase3ID":109575,"n_Phase3Nr":10,"c_Phase3":"Groep J","b_Table":true,"b_Current":false,"b_Currents":false,"n_DateStart":20140918,"n_DateEnd":20141211},{"n_PhaseID":109576,"n_PhaseLevel":33,"c_Phase":"Groep K","n_Phase1ID":109555,"n_Phase1Nr":2,"c_Phase1":"Hoofdtoernooi","n_Phase2ID":109560,"n_Phase2Nr":5,"c_Phase2":"Groepsfase","n_Phase3ID":109576,"n_Phase3Nr":11,"c_Phase3":"Groep K","b_Table":true,"b_Current":false,"b_Currents":false,"n_DateStart":20140918,"n_DateEnd":20141211},{"n_PhaseID":109577,"n_PhaseLevel":33,"c_Phase":"Groep L","n_Phase1ID":109555,"n_Phase1Nr":2,"c_Phase1":"Hoofdtoernooi","n_Phase2ID":109560,"n_Phase2Nr":5,"c_Phase2":"Groepsfase","n_Phase3ID":109577,"n_Phase3Nr":12,"c_Phase3":"Groep L","b_Table":true,"b_Current":false,"b_Currents":false,"n_DateStart":20140918,"n_DateEnd":20141211},{"n_PhaseID":109561,"n_PhaseLevel":17,"c_Phase":"Laatste 32","n_Phase1ID":109555,"n_Phase1Nr":2,"c_Phase1":"Hoofdtoernooi","n_Phase2ID":109561,"n_Phase2Nr":6,"c_Phase2":"Laatste 32","n_Phase3ID":null,"n_Phase3Nr":null,"c_Phase3":null,"b_Table":false,"b_Current":true,"b_Currents":true,"n_DateStart":20150219,"n_DateEnd":20150226},{"n_PhaseID":109562,"n_PhaseLevel":9,"c_Phase":"Laatste 16","n_Phase1ID":109555,"n_Phase1Nr":2,"c_Phase1":"Hoofdtoernooi","n_Phase2ID":109562,"n_Phase2Nr":7,"c_Phase2":"Laatste 16","n_Phase3ID":null,"n_Phase3Nr":null,"c_Phase3":null,"b_Table":false,"b_Current":false,"b_Currents":false,"n_DateStart":20150312,"n_DateEnd":20150319},{"n_PhaseID":109563,"n_PhaseLevel":5,"c_Phase":"Kwartfinale","n_Phase1ID":109555,"n_Phase1Nr":2,"c_Phase1":"Hoofdtoernooi","n_Phase2ID":109563,"n_Phase2Nr":8,"c_Phase2":"Kwartfinale","n_Phase3ID":null,"n_Phase3Nr":null,"c_Phase3":null,"b_Table":false,"b_Current":false,"b_Currents":false,"n_DateStart":20150416,"n_DateEnd":20150423},{"n_PhaseID":109564,"n_PhaseLevel":3,"c_Phase":"Halve finale","n_Phase1ID":109555,"n_Phase1Nr":2,"c_Phase1":"Hoofdtoernooi","n_Phase2ID":109564,"n_Phase2Nr":9,"c_Phase2":"Halve finale","n_Phase3ID":null,"n_Phase3Nr":null,"c_Phase3":null,"b_Table":false,"b_Current":false,"b_Currents":false,"n_DateStart":20150507,"n_DateEnd":20150514},{"n_PhaseID":109565,"n_PhaseLevel":2,"c_Phase":"Finale","n_Phase1ID":109555,"n_Phase1Nr":2,"c_Phase1":"Hoofdtoernooi","n_Phase2ID":109565,"n_Phase2Nr":10,"c_Phase2":"Finale","n_Phase3ID":null,"n_Phase3Nr":null,"c_Phase3":null,"b_Table":false,"b_Current":false,"b_Currents":false,"n_DateStart":20150527,"n_DateEnd":20150527}]