[{"n_EditionID":21197,"c_Phase":"Group E","n_TeamID":4045,"c_Team":"Dinamo Moskva","c_TeamShort":"DMO","n_TeamNatioGeoID":2204,"c_TeamNatio":"Russia","c_TeamNatioShort":"RUS","n_RankSort":1,"c_Rank":"1","n_RankCode":1024,"n_MinRank":1,"n_MinRankCode":1024,"n_MaxRank":1,"n_MaxRankCode":1024,"n_PrevRankSort":null,"n_PrevRank":null,"n_Matches":6,"n_MatchesWon":6,"n_MatchesDrawn":0,"n_MatchesLost":0,"n_Points":18,"n_GoalsFor":9,"n_GoalsAgainst":3,"n_HomeMatches":3,"n_HomeMatchesWon":3,"n_HomeMatchesDrawn":0,"n_HomeMatchesLost":0,"n_HomePoints":9,"n_HomeGoalsFor":4,"n_HomeGoalsAgainst":1,"n_AwayMatches":3,"n_AwayMatchesWon":3,"n_AwayMatchesDrawn":0,"n_AwayMatchesLost":0,"n_AwayPoints":9,"n_AwayGoalsFor":5,"n_AwayGoalsAgainst":2},{"n_EditionID":21197,"c_Phase":"Group E","n_TeamID":11,"c_Team":"PSV","c_TeamShort":"PSV","n_TeamNatioGeoID":2201,"c_TeamNatio":"Netherlands","c_TeamNatioShort":"NED","n_RankSort":2,"c_Rank":"2","n_RankCode":1024,"n_MinRank":2,"n_MinRankCode":1024,"n_MaxRank":2,"n_MaxRankCode":1024,"n_PrevRankSort":null,"n_PrevRank":null,"n_Matches":6,"n_MatchesWon":2,"n_MatchesDrawn":2,"n_MatchesLost":2,"n_Points":8,"n_GoalsFor":8,"n_GoalsAgainst":8,"n_HomeMatches":3,"n_HomeMatchesWon":1,"n_HomeMatchesDrawn":1,"n_HomeMatchesLost":1,"n_HomePoints":4,"n_HomeGoalsFor":2,"n_HomeGoalsAgainst":2,"n_AwayMatches":3,"n_AwayMatchesWon":1,"n_AwayMatchesDrawn":1,"n_AwayMatchesLost":1,"n_AwayPoints":4,"n_AwayGoalsFor":6,"n_AwayGoalsAgainst":6},{"n_EditionID":21197,"c_Phase":"Group E","n_TeamID":103013,"c_Team":"GD Estoril Praia","c_TeamShort":"EST","n_TeamNatioGeoID":2223,"c_TeamNatio":"Portugal","c_TeamNatioShort":"POR","n_RankSort":3,"c_Rank":"3","n_RankCode":0,"n_MinRank":3,"n_MinRankCode":0,"n_MaxRank":3,"n_MaxRankCode":0,"n_PrevRankSort":null,"n_PrevRank":null,"n_Matches":6,"n_MatchesWon":1,"n_MatchesDrawn":2,"n_MatchesLost":3,"n_Points":5,"n_GoalsFor":7,"n_GoalsAgainst":8,"n_HomeMatches":3,"n_HomeMatchesWon":1,"n_HomeMatchesDrawn":1,"n_HomeMatchesLost":1,"n_HomePoints":4,"n_HomeGoalsFor":6,"n_HomeGoalsAgainst":5,"n_AwayMatches":3,"n_AwayMatchesWon":0,"n_AwayMatchesDrawn":1,"n_AwayMatchesLost":2,"n_AwayPoints":1,"n_AwayGoalsFor":1,"n_AwayGoalsAgainst":3},{"n_EditionID":21197,"c_Phase":"Group E","n_TeamID":4218,"c_Team":"Panathinaikos","c_TeamShort":"PAN","n_TeamNatioGeoID":2774,"c_TeamNatio":"Greece","c_TeamNatioShort":"GRE","n_RankSort":4,"c_Rank":"4","n_RankCode":0,"n_MinRank":4,"n_MinRankCode":0,"n_MaxRank":4,"n_MaxRankCode":0,"n_PrevRankSort":null,"n_PrevRank":null,"n_Matches":6,"n_MatchesWon":0,"n_MatchesDrawn":2,"n_MatchesLost":4,"n_Points":2,"n_GoalsFor":6,"n_GoalsAgainst":11,"n_HomeMatches":3,"n_HomeMatchesWon":0,"n_HomeMatchesDrawn":1,"n_HomeMatchesLost":2,"n_HomePoints":1,"n_HomeGoalsFor":4,"n_HomeGoalsAgainst":6,"n_AwayMatches":3,"n_AwayMatchesWon":0,"n_AwayMatchesDrawn":1,"n_AwayMatchesLost":2,"n_AwayPoints":1,"n_AwayGoalsFor":2,"n_AwayGoalsAgainst":5}]